hyperSIS/__init__.py
hyperSIS/core.py
hyperSIS/io_utils.py
hyperSIS/types.py
hyperSIS/bin/hyperSIS_sampling
hyperSIS/bin/hyperSIS_sampling.py
hypersis-1.2.0.dist-info/METADATA
hypersis-1.2.0.dist-info/WHEEL
hypersis-1.2.0.dist-info/entry_points.txt
hypersis-1.2.0.dist-info/top_level.txt
hypersis-1.2.0.dist-info/RECORD
